Workbook

Sheet Assumptions
A1: Producer Settlement & Equalization Model
A2: Sample facility: shared battery, monthly settlement, hypothetical data for portfolio demonstration
A4: Legend
A5: Blue text = input (edit these)
A6: Black text = formula (do not edit)
A7: Yellow fill = key assumption
A9: Facility Name | B9: Wapiti Shared Battery 04-12
A10: Settlement Month | B10: July 2026
A11: Total Facility Operating Cost ($) | B11: 42500
A12: Sales Price ($ / bbl) — WTI Cushing Spot, Jul 2026 Monthly Avg | B12: 79.71 | C12: Source: U.S. EIA, WTI Cushing OK Spot Price, monthly avg, retrieved Aug 2026
A13: Facility Shrinkage Rate (%) | B13: 0.012
A16: Data Source Note
A17: Sales price is real, publicly sourced market data (see cell C12).
A18: Producer names, LSDs, volumes, meter quality factors, operating cost, and shrinkage rate are hypothetical, constructed for demonstration purposes.

Sheet Volume Allocation
A1: Volume Allocation & Equalization
A2: LSD = Legal Subdivision (Alberta land/well identifier)
A4: Producer | B4: LSD | C4: Metered Volume Delivered (bbl) | D4: Meter Quality Factor | E4: Equalized Volume (bbl) | F4: % of Total Equalized Volume
A5: Cardium Resources Ltd. | B5: 04-12-063-08W6 | C5: 3120 | D5: 0.998 | E5: =C5*D5 -> 3113.76 | F5: =E5/$E$9 -> 0.25630101
A6: Northgate Energy Corp. | B6: 09-12-063-08W6 | C6: 2685 | D6: 1.002 | E6: =C6*D6 -> 2690.37 | F6: =E6/$E$9 -> 0.22145077
A7: Prairie Sky Producers | B7: 16-12-063-08W6 | C7: 1940 | D7: 0.995 | E7: =C7*D7 -> 1930.3 | F7: =E7/$E$9 -> 0.1588876
A8: Foothills Oil Partners | B8: 22-12-063-08W6 | C8: 4410 | D8: 1.001 | E8: =C8*D8 -> 4414.41 | F8: =E8/$E$9 -> 0.36336062
A9: Total | C9: =SUM(C5:C8) -> 12155 | E9: =SUM(E5:E8) -> 12148.84

Sheet Settlement Summary
A1: Monthly Settlement Summary
A2: ="Facility: "&Assumptions!B9&" | Period: "&Assumptions!B10 -> Facility: Wapiti Shared Battery 04-12 | Period: July 2026
A4: Producer | B4: % of Total Equalized Volume | C4: Gross Volume Post-Shrinkage (bbl) | D4: Gross Revenue ($) | E4: Allocated Operating Cost ($) | F4: Net Settlement ($)
A5: ='Volume Allocation'!A5 -> Cardium Resources Ltd. | B5: ='Volume Allocation'!F5 -> 0.25630101 | C5: ='Volume Allocation'!E5*(1-Assumptions!$B$13) -> 3076.3949 | D5: =C5*Assumptions!$B$12 -> 245219.44 | E5: =B5*Assumptions!$B$11 -> 10892.793 | F5: =D5-E5 -> 234326.64
A6: ='Volume Allocation'!A6 -> Northgate Energy Corp. | B6: ='Volume Allocation'!F6 -> 0.22145077 | C6: ='Volume Allocation'!E6*(1-Assumptions!$B$13) -> 2658.0856 | D6: =C6*Assumptions!$B$12 -> 211876 | E6: =B6*Assumptions!$B$11 -> 9411.6578 | F6: =D6-E6 -> 202464.34
A7: ='Volume Allocation'!A7 -> Prairie Sky Producers | B7: ='Volume Allocation'!F7 -> 0.1588876 | C7: ='Volume Allocation'!E7*(1-Assumptions!$B$13) -> 1907.1364 | D7: =C7*Assumptions!$B$12 -> 152017.84 | E7: =B7*Assumptions!$B$11 -> 6752.7229 | F7: =D7-E7 -> 145265.12
A8: ='Volume Allocation'!A8 -> Foothills Oil Partners | B8: ='Volume Allocation'!F8 -> 0.36336062 | C8: ='Volume Allocation'!E8*(1-Assumptions!$B$13) -> 4361.4371 | D8: =C8*Assumptions!$B$12 -> 347650.15 | E8: =B8*Assumptions!$B$11 -> 15442.826 | F8: =D8-E8 -> 332207.32
A9: Total | D9: =SUM(D5:D8) -> 956763.43 | E9: =SUM(E5:E8) -> 42500 | F9: =SUM(F5:F8) -> 914263.43
A12: Notes:
A13: Equalized volume = metered volume x meter quality factor, adjusting each producer's raw delivered volume for meter calibration variance.
A14: Operating cost is allocated pro-rata by each producer's share of total equalized volume, consistent with standard shared-facility cost-allocation practice.
A15: Shrinkage rate applied at the facility level before revenue calculation, representing measurement and processing losses.
